LICENSE
README.md
rise.py
setup.py
captum_rise.egg-info/PKG-INFO
captum_rise.egg-info/SOURCES.txt
captum_rise.egg-info/dependency_links.txt
captum_rise.egg-info/requires.txt
captum_rise.egg-info/top_level.txt