Metadata-Version: 2.1
Name: captum-rise
Version: 1.0
Summary: The implementation of the RISE algorithm for the Captum framework
Home-page: https://github.com/indirivacua/captum-rise
Author: Oscar Agustín Stanchi
Author-email: oscar.stanchi@gmail.com
License: BSD-3-Clause
Project-URL: Bug Tracker, https://github.com/indirivacua/captum-rise/issues
Project-URL: Documentation, https://github.com/indirivacua/captum-rise
Project-URL: Source Code, https://github.com/indirivacua/captum-rise
Keywords: Black-Box Computer-Vision Deep-Learning Interpretability RISE
Classifier: License :: OSI Approved :: BSD License
Classifier: Programming Language :: Python :: 3.8
Classifier: Development Status :: 4 - Beta
Classifier: Intended Audience :: Developers
Classifier: Topic :: Scientific/Engineering :: Artificial Intelligence
Requires-Python: >=3.8
License-File: LICENSE
